llama_index/storage/index_store/elasticsearch/__init__.py
llama_index/storage/index_store/elasticsearch/base.py
llama_index_storage_index_store_elasticsearch-0.5.1.dist-info/METADATA
llama_index_storage_index_store_elasticsearch-0.5.1.dist-info/WHEEL
llama_index_storage_index_store_elasticsearch-0.5.1.dist-info/licenses/LICENSE
llama_index_storage_index_store_elasticsearch-0.5.1.dist-info/RECORD
